[
    { "Name": "AzusaCat", "href": "https://AzusaCat1111.github.io/" },
    { "Name": "AlanSP", "href": "https://alan-sp.github.io/" },
    { "Name": "hs-black", "href": "https://www.cnblogs.com/Hs-black/" },
    { "Name": "lhm_", "href": "https://www.cnblogs.com/lhm-/" },
    { "Name": "BlueQuantum", "href": "https://bluequantum.gitee.io/" },
    { "Name": "Hercules", "href": "https://www.luogu.com.cn/blog/hercules/" },
    { "Name": "RenaMoe", "href": "https://renamoe.gitee.io/" },
    { "Name": "STDquantum", "href": "https://stdquantum.gitee.io/" },
    { "Name": "Jasony", "href": "https://www.luogu.com.cn/blog/jasony/" },
    { "Name": "Sky", "href": "https://www.cnblogs.com/shikeyu/" },
    { "Name": "ChPu437", "href": "https://chpu437.gitee.io/" }
]